sllm/__init__.py
srvllm-0.0.0.dist-info/LICENSE
srvllm-0.0.0.dist-info/METADATA
srvllm-0.0.0.dist-info/WHEEL
srvllm-0.0.0.dist-info/top_level.txt
srvllm-0.0.0.dist-info/RECORD
