Metadata-Version: 2.1
Name: srvllm
Version: 0.0.0
Summary: A brief description of sl-llm
Author: Yao Fu
Classifier: Programming Language :: Python :: 3
Classifier: License :: OSI Approved :: MIT License
Classifier: Operating System :: OS Independent
Requires-Python: >=3.6
License-File: LICENSE
